[
    {
        "file_name": "Chapter_13_msk_FIG_1.jpg",
        "section": "Musculoskeletal Imaging Chapter_13_msk Page: 144",
        "ocr_caption": "SHOULDER LIGAMENTS AND ROTATOR INTERVAL\nAnatomy of the shoulder ligaments\ncoracoid\nacromion\nprocess\ncoracohumeral\nligament (CHL)\nattaches to\ngreater\nrotator interval contains CHL, LHBT, and SGHL\ntuberosity\nSGHL\nsuperior glenohumeral ligament (SGHL) and\nMGHL\nmiddles glenohumeraligament. (MGHL) connect the\nlesser tuberosity tot the supraglenoidi tubercle ofthes scapula.\n=\nlong head\nbiceps\nIGHL\nthe inferior glenohumeral ligament (IGHL) connects the the\ntendon\ninferiorg glenoid labrum with thec anatomicr neck ofthel humerus.\n(LHBT)\nThe rotator interval is a triangular region that allows rotational motion around the coracoid\nprocess. It is located between the supraspinatus and subscapularis tendons. The rotator\ninterval contains the coracohumeral ligament (CHL), the long head of the biceps tendon\n(LHBT), and the superior glenohumeral ligament (SGHL).\nThe CHL connects the lateral aspect of the coracoid process to the greater tubercle of the\nhumerus, where the CHL blends with the supraspinatus tendon. The CHL helps to stabilize\nthe intra-articular biceps tendon together with the superior glenohumeral ligament as the\nbiceps pulley. The CHL is located external to the joint capsule.\nThe glenohumera. ligaments (SGHL, MGHL, and IGHL) are derived from the labrum and form\na portion of the joint capsule.\nThe superior glenohumeral ligament (SGHL) connects the lesser tuberosity to the\nsupraglenoid tubercle of the scapula.\nThe middle glenohumeral ligament (MGHL) also connects the lesser tuberosity to the\nsupraglenoid tubercle of the scapula. The MGHL is congenitally absent in up to 1/3 of\npatients. Tears of the MGHL are associated with SLAP lesions.\nThe inferior glenohumeral ligament (IGHL) connects the anatomic neck of the humerus\nto the inferior glenoid labrum. The IGHL is by far the most important component of the\ncapsulolabral complex for maintaining stability in abduction and external rotation. The IGHL\ncontains three components (the anterior band, the axillary pouch, and the posterior band),\nall of which are well-seen on sagittal MR:\nThe anterior band of the IGHL provides anterior stability. There are several lesions of the anterior band of\nthe IGHL that are associated with anterior instability, discussed on the following page.\nThe IGHL forms the axillary pouch of the glenohumeral joint capsule.\nThe posterior band contributes to posterior stability. The IGHL is the only glenohumeral ligament to have a\nposterior component.\nThe long head biceps tendon (LHBT) attaches to the anterosuperior glenoid rim along with\nthe SGHL and MGHL.\nMSK: 1051"
    },
    {
        "file_name": "Chapter_13_msk_FIG_2.jpg",
        "section": "Musculoskeletal Imaging Chapter_13_msk Page: 144",
        "ocr_caption": "SHOULDER LIGAMENTS AND ROTATOR INTERVAL\nAnatomy of the shoulder ligaments\ncoracoid\nacromion\nprocess\ncoracohumeral\nligament (CHL)\nattaches to\ngreater\nrotator interval contains CHL, LHBT, and SGHL\ntuberosity\nSGHL\nsuperior glenohumeral ligament (SGHL) and\nMGHL\nmiddles glenohumeraligament. (MGHL) connect the\nlesser tuberosity tot the supraglenoidi tubercle ofthes scapula.\n=\nlong head\nbiceps\nIGHL\nthe inferior glenohumeral ligament (IGHL) connects the the\ntendon\ninferiorg glenoid labrum with thec anatomicr neck ofthel humerus.\n(LHBT)\nThe rotator interval is a triangular region that allows rotational motion around the coracoid\nprocess. It is located between the supraspinatus and subscapularis tendons. The rotator\ninterval contains the coracohumeral ligament (CHL), the long head of the biceps tendon\n(LHBT), and the superior glenohumeral ligament (SGHL).\nThe CHL connects the lateral aspect of the coracoid process to the greater tubercle of the\nhumerus, where the CHL blends with the supraspinatus tendon. The CHL helps to stabilize\nthe intra-articular biceps tendon together with the superior glenohumeral ligament as the\nbiceps pulley. The CHL is located external to the joint capsule.\nThe glenohumera. ligaments (SGHL, MGHL, and IGHL) are derived from the labrum and form\na portion of the joint capsule.\nThe superior glenohumeral ligament (SGHL) connects the lesser tuberosity to the\nsupraglenoid tubercle of the scapula.\nThe middle glenohumeral ligament (MGHL) also connects the lesser tuberosity to the\nsupraglenoid tubercle of the scapula. The MGHL is congenitally absent in up to 1/3 of\npatients. Tears of the MGHL are associated with SLAP lesions.\nThe inferior glenohumeral ligament (IGHL) connects the anatomic neck of the humerus\nto the inferior glenoid labrum. The IGHL is by far the most important component of the\ncapsulolabral complex for maintaining stability in abduction and external rotation. The IGHL\ncontains three components (the anterior band, the axillary pouch, and the posterior band),\nall of which are well-seen on sagittal MR:\nThe anterior band of the IGHL provides anterior stability. There are several lesions of the anterior band of\nthe IGHL that are associated with anterior instability, discussed on the following page.\nThe IGHL forms the axillary pouch of the glenohumeral joint capsule.\nThe posterior band contributes to posterior stability. The IGHL is the only glenohumeral ligament to have a\nposterior component.\nThe long head biceps tendon (LHBT) attaches to the anterosuperior glenoid rim along with\nthe SGHL and MGHL.\nMSK: 1051"
    }
]