[
    {
        "file_name": "Chapter_10_neurobrain_FIG_1.jpg",
        "section": "Neuroimaging: Brain Chapter_10_neurobrain Page: 77",
        "ocr_caption": "Intra-axial metastasis (continued)\nThe most common hemorrhagic metastases to the brain are melanoma, renal cell\ncarcinoma, choriocarcinoma, and thyroid cancer (especially papillary carcinoma). Breast\nand lung cancer are also included in this differential due to their high prevalence, although\nhemorrhagic metastases are an atypical presentation.\nThe main causes of a solitary hemorrhagic brain neoplasm are metastatic carcinomas and glioblastoma.\nTumorous intracerebral hemorrhage may be difficult to distinguish initially from primary intracerebral\nhemorrhage (such as due to hypertension or amyloid angiopathy) but should be suspected by the\npresence of an enhancing component or failure to resolve on follow-up.\nExtra-axial metastasis\nLeptomeningeal metastases, also known as carcinomatous meningitis, appears as serpentine\ncontrast enhancement at the pial surface of the brain. FLAIR shows sulcal hyperintensity.\nThe main causes of leptomeningeal enhancement and sulcal FLAIR hyperintensity are infectious/\ninflammatory meningitis and metastases. Nonenhancing sulcal FLAIR hyperintensity can also be caused by\nsubarachnoid hemorrhage.\nDural metastases appear as focal enhancing extra-axial masses.\nThe main causes of multiple dural masses are multiple meningiomatosis and metastases.\nAxial FLAIR (left image) shows a right frontal mass (yellow arrows) with vasogenic edema affecting the right\nfrontal lobe. From this image alone it is difficult to determine if the mass is intra- or extra-axial. Axial post-\ncontrast T1-weighted (right image) MRI shows that the mass (yellow arrow) is dural based and is associated\nwith adjacent dural enhancement (red arrows). This was a case of metastatic breast cancer.\nNeuro Brain: 726"
    },
    {
        "file_name": "Chapter_10_neurobrain_FIG_2.jpg",
        "section": "Neuroimaging: Brain Chapter_10_neurobrain Page: 77",
        "ocr_caption": "Intra-axial metastasis (continued)\nThe most common hemorrhagic metastases to the brain are melanoma, renal cell\ncarcinoma, choriocarcinoma, and thyroid cancer (especially papillary carcinoma). Breast\nand lung cancer are also included in this differential due to their high prevalence, although\nhemorrhagic metastases are an atypical presentation.\nThe main causes of a solitary hemorrhagic brain neoplasm are metastatic carcinomas and glioblastoma.\nTumorous intracerebral hemorrhage may be difficult to distinguish initially from primary intracerebral\nhemorrhage (such as due to hypertension or amyloid angiopathy) but should be suspected by the\npresence of an enhancing component or failure to resolve on follow-up.\nExtra-axial metastasis\nLeptomeningeal metastases, also known as carcinomatous meningitis, appears as serpentine\ncontrast enhancement at the pial surface of the brain. FLAIR shows sulcal hyperintensity.\nThe main causes of leptomeningeal enhancement and sulcal FLAIR hyperintensity are infectious/\ninflammatory meningitis and metastases. Nonenhancing sulcal FLAIR hyperintensity can also be caused by\nsubarachnoid hemorrhage.\nDural metastases appear as focal enhancing extra-axial masses.\nThe main causes of multiple dural masses are multiple meningiomatosis and metastases.\nAxial FLAIR (left image) shows a right frontal mass (yellow arrows) with vasogenic edema affecting the right\nfrontal lobe. From this image alone it is difficult to determine if the mass is intra- or extra-axial. Axial post-\ncontrast T1-weighted (right image) MRI shows that the mass (yellow arrow) is dural based and is associated\nwith adjacent dural enhancement (red arrows). This was a case of metastatic breast cancer.\nNeuro Brain: 726"
    }
]