[
    {
        "file_name": "Chapter_12_spine_FIG_1.jpg",
        "section": "Spine Imaging Chapter_12_spine Page: 44",
        "ocr_caption": "THORACOLUMBAR SPINE TRAUMA\nOverview of thoracolumbar trauma\nThe thoracolumbar injury classification and severity score (TLICS) is similar to SLICS for the\ncervical (subaxial) spine, and aids in determination of optimal treatment.\nThe TLICS provides a numerical score for injury severity based on the same three\ncomponents of SLICS: injury morphology, integrity of the posterior ligamentous complex\n(PLC), and neurological status.\nThe PLC is a primary stabilizer of the posterior spinal column, and knowledge of its anatomy\nis helpful to recognize potentially unstable injuries. Indirect imaging findings of PLC injury\ninclude widening of the interspinous distance, widening of the facet joints, spinous process\nfracture, and subluxation or dislocation of a vertebral body.\nRigid spine trauma\nSagittal CT\nSagittal STIR MRI\nRigid spine hyperextension injury in a patient with\ndiffuse idiopathic skeletal hyperostosis (DISH):\nCT demonstrates marked widening of the T12-L1 disc\nspace (yellow arrows), in keeping with hyperextension\ninjury. Note the tiny retropulsed fracture fragment\n(red arrow). Multilevel flowing anterior osteophytes\nare partially seen.\nMRI confirms fluid in the disc space (yellow arrows).\nThere is an epidural hematoma (red arrows)\ncontributing to severe spinal stenosis. There is edema\nin the region of the anterior longitudinal ligament\n(blue arrow), consistent with disruption. Note the\nsuperior endplate fracture of L1 (green arrow).\nAxial T2-weighted MR\nPatients with a rigid spine - due to diffusion idiopathic skeletal hyperostosis (DISH),\nankylosing spondylitis, degenerative change, or surgical fusion, are more vulnerable to\nfracture given altered biomechanics.\nCT should be performed in a patient with rigid spine and back pain after even minor trauma.\nHyperextension is the most common injury mechanism.\nSpine: 903"
    },
    {
        "file_name": "Chapter_12_spine_FIG_2.jpg",
        "section": "Spine Imaging Chapter_12_spine Page: 44",
        "ocr_caption": "THORACOLUMBAR SPINE TRAUMA\nOverview of thoracolumbar trauma\nThe thoracolumbar injury classification and severity score (TLICS) is similar to SLICS for the\ncervical (subaxial) spine, and aids in determination of optimal treatment.\nThe TLICS provides a numerical score for injury severity based on the same three\ncomponents of SLICS: injury morphology, integrity of the posterior ligamentous complex\n(PLC), and neurological status.\nThe PLC is a primary stabilizer of the posterior spinal column, and knowledge of its anatomy\nis helpful to recognize potentially unstable injuries. Indirect imaging findings of PLC injury\ninclude widening of the interspinous distance, widening of the facet joints, spinous process\nfracture, and subluxation or dislocation of a vertebral body.\nRigid spine trauma\nSagittal CT\nSagittal STIR MRI\nRigid spine hyperextension injury in a patient with\ndiffuse idiopathic skeletal hyperostosis (DISH):\nCT demonstrates marked widening of the T12-L1 disc\nspace (yellow arrows), in keeping with hyperextension\ninjury. Note the tiny retropulsed fracture fragment\n(red arrow). Multilevel flowing anterior osteophytes\nare partially seen.\nMRI confirms fluid in the disc space (yellow arrows).\nThere is an epidural hematoma (red arrows)\ncontributing to severe spinal stenosis. There is edema\nin the region of the anterior longitudinal ligament\n(blue arrow), consistent with disruption. Note the\nsuperior endplate fracture of L1 (green arrow).\nAxial T2-weighted MR\nPatients with a rigid spine - due to diffusion idiopathic skeletal hyperostosis (DISH),\nankylosing spondylitis, degenerative change, or surgical fusion, are more vulnerable to\nfracture given altered biomechanics.\nCT should be performed in a patient with rigid spine and back pain after even minor trauma.\nHyperextension is the most common injury mechanism.\nSpine: 903"
    }
]